{"cameraMode":{"drawMode":0,"name":"Shaded","section":"Shading Mode"},"sceneLighting":false,"audioPlay":false,"sceneViewState":{"showFog":true,"showMaterialUpdate":false,"showSkybox":false,"showFlares":true,"showImageEffects":true,"showParticleSystems":true},"in2DMode":false,"pivot":{"x":-5.893702983856201,"y":-8.878793716430664,"z":-8.807472229003907},"rotation":{"x":-0.09757827967405319,"y":0.7978575229644775,"z":-0.13433893024921418,"w":-0.5795311331748962},"size":7.411971569061279,"orthographic":false}